h5record/__init__.py
h5record/attributes.py
h5record/dataset.py
h5record-1.0.4.dist-info/LICENSE
h5record-1.0.4.dist-info/METADATA
h5record-1.0.4.dist-info/WHEEL
h5record-1.0.4.dist-info/top_level.txt
h5record-1.0.4.dist-info/RECORD
