Metadata-Version: 2.1
Name: h5record
Version: 1.0.4
Summary: Large data storage for pytorch
Home-page: https://github.com/theblackcat102/h5record
Author: theblackcat
Author-email: zhirui09400@gmail.com
License: MIT License
Keywords: data processing
Platform: UNKNOWN
Classifier: Development Status :: 5 - Production/Stable
Classifier: Intended Audience :: Developers
Classifier: License :: OSI Approved :: Apache Software License
Classifier: Operating System :: OS Independent
Classifier: Programming Language :: Python :: 3
Classifier: Programming Language :: Python :: 3.6
Classifier: Programming Language :: Python :: 3.7
Classifier: Programming Language :: Python :: 3.8
Requires-Dist: torch
Requires-Dist: h5py
Requires-Dist: numpy
